pygameElements/__init__.py
pygameElements/pygameElements.py
testPygameElements/__init__.py
testPygameElements/testPygameElements.py
testPygameElements/fonts/Ballpointprint.ttf
testPygameElements/images/SquareExamples.png
testPygameElements/images/someimage.png
pygameelements-0.1.56.dist-info/LICENSE
pygameelements-0.1.56.dist-info/LICENSE.txt
pygameelements-0.1.56.dist-info/METADATA
pygameelements-0.1.56.dist-info/WHEEL
pygameelements-0.1.56.dist-info/top_level.txt
pygameelements-0.1.56.dist-info/RECORD
