Metadata-Version: 2.1
Name: pygameelements
Version: 0.1.56
Summary: Elements that scale with screensize for pygame
Home-page: https://github.com/QuetzalQatl/PyGameElements
Author: Bas Koning
Author-email: basknng@gmail.com
License: MIT
Download-URL: https://github.com/QuetzalQatl/PyGameElements/blob/main/dist/pygameelements-0.1.56.tar.gz
Keywords: pygame,element,gui,button,label,text,image,checkbox,inputbox,line,square,ellipse,test
Platform: UNKNOWN
Classifier: Development Status :: 3 - Alpha
Classifier: Intended Audience :: Developers
Classifier: Topic :: Software Development :: Build Tools
Classifier: License :: OSI Approved :: MIT License
Classifier: Programming Language :: Python :: 3.6
Classifier: Programming Language :: Python :: 3.7
Classifier: Programming Language :: Python :: 3.8
Classifier: Programming Language :: Python :: 3.9
Classifier: Operating System :: OS Independent
Requires-Dist: pygame
Requires-Dist: pygameelements
